{"name":"Projet 1","image":"https://via.placeholder.com/150","stats":{"total":51689,"sessions":[{"words":776,"date":"2021-01-1","hours":16,"minutes":15,"mood":0,"notes":"Lorem ipsum dolor sit amet, consectetur adipiscing elit. Nulla ac nisi nec odio"},{"words":946,"date":"2021-01-2","hours":23,"minutes":0,"mood":4,"notes":"Lorem ipsum dolor sit amet, consectetur adipiscing elit. Nulla ac nisi nec odio"},{"words":563,"date":"2021-01-3","hours":11,"minutes":58,"mood":3,"notes":"Lorem ipsum dolor sit amet, consectetur adipiscing elit. Nulla ac nisi nec odio"},{"words":452,"date":"2021-01-4","hours":19,"minutes":10,"mood":2,"notes":"Lorem ipsum dolor sit amet, consectetur adipiscing elit. Nulla ac nisi nec odio"},{"words":299,"date":"2021-01-5","hours":18,"minutes":14,"mood":2,"notes":"Lorem ipsum dolor sit amet, consectetur adipiscing elit. Nulla ac nisi nec odio"},{"words":825,"date":"2021-01-6","hours":23,"minutes":53,"mood":3,"notes":"Lorem ipsum dolor sit amet, consectetur adipiscing elit. Nulla ac nisi nec odio"},{"words":264,"date":"2021-01-7","hours":14,"minutes":43,"mood":3,"notes":"Lorem ipsum dolor sit amet, consectetur adipiscing elit. Nulla ac nisi nec odio"},{"words":73,"date":"2021-01-8","hours":12,"minutes":28,"mood":1,"notes":"Lorem ipsum dolor sit amet, consectetur adipiscing elit. Nulla ac nisi nec odio"},{"words":711,"date":"2021-01-9","hours":12,"minutes":54,"mood":4,"notes":"Lorem ipsum dolor sit amet, consectetur adipiscing elit. Nulla ac nisi nec odio"},{"words":519,"date":"2021-01-10","hours":9,"minutes":55,"mood":0,"notes":"Lorem ipsum dolor sit amet, consectetur adipiscing elit. Nulla ac nisi nec odio"},{"words":554,"date":"2021-01-11","hours":9,"minutes":28,"mood":3,"notes":"Lorem ipsum dolor sit amet, consectetur adipiscing elit. Nulla ac nisi nec odio"},{"words":800,"date":"2021-01-12","hours":1,"minutes":26,"mood":1,"notes":"Lorem ipsum dolor sit amet, consectetur adipiscing elit. Nulla ac nisi nec odio"},{"words":390,"date":"2021-01-13","hours":5,"minutes":12,"mood":1,"notes":"Lorem ipsum dolor sit amet, consectetur adipiscing elit. Nulla ac nisi nec odio"},{"words":960,"date":"2021-01-14","hours":12,"minutes":45,"mood":4,"notes":"Lorem ipsum dolor sit amet, consectetur adipiscing elit. Nulla ac nisi nec odio"},{"words":839,"date":"2021-01-15","hours":2,"minutes":33,"mood":0,"notes":"Lorem ipsum dolor sit amet, consectetur adipiscing elit. Nulla ac nisi nec odio"},{"words":989,"date":"2021-01-16","hours":11,"minutes":23,"mood":0,"notes":"Lorem ipsum dolor sit amet, consectetur adipiscing elit. Nulla ac nisi nec odio"},{"words":780,"date":"2021-01-17","hours":8,"minutes":20,"mood":4,"notes":"Lorem ipsum dolor sit amet, consectetur adipiscing elit. Nulla ac nisi nec odio"},{"words":778,"date":"2021-01-18","hours":5,"minutes":26,"mood":4,"notes":"Lorem ipsum dolor sit amet, consectetur adipiscing elit. Nulla ac nisi nec odio"},{"words":410,"date":"2021-01-19","hours":19,"minutes":31,"mood":4,"notes":"Lorem ipsum dolor sit amet, consectetur adipiscing elit. Nulla ac nisi nec odio"},{"words":208,"date":"2021-01-20","hours":23,"minutes":46,"mood":0,"notes":"Lorem ipsum dolor sit amet, consectetur adipiscing elit. Nulla ac nisi nec odio"},{"words":261,"date":"2021-01-21","hours":14,"minutes":21,"mood":0,"notes":"Lorem ipsum dolor sit amet, consectetur adipiscing elit. Nulla ac nisi nec odio"},{"words":261,"date":"2021-01-22","hours":14,"minutes":35,"mood":1,"notes":"Lorem ipsum dolor sit amet, consectetur adipiscing elit. Nulla ac nisi nec odio"},{"words":697,"date":"2021-01-23","hours":11,"minutes":33,"mood":3,"notes":"Lorem ipsum dolor sit amet, consectetur adipiscing elit. Nulla ac nisi nec odio"},{"words":396,"date":"2021-01-24","hours":9,"minutes":31,"mood":3,"notes":"Lorem ipsum dolor sit amet, consectetur adipiscing elit. Nulla ac nisi nec odio"},{"words":828,"date":"2021-01-25","hours":11,"minutes":25,"mood":1,"notes":"Lorem ipsum dolor sit amet, consectetur adipiscing elit. Nulla ac nisi nec odio"},{"words":998,"date":"2021-01-26","hours":9,"minutes":5,"mood":0,"notes":"Lorem ipsum dolor sit amet, consectetur adipiscing elit. Nulla ac nisi nec odio"},{"words":213,"date":"2021-01-27","hours":8,"minutes":4,"mood":3,"notes":"Lorem ipsum dolor sit amet, consectetur adipiscing elit. Nulla ac nisi nec odio"},{"words":439,"date":"2021-01-28","hours":23,"minutes":45,"mood":4,"notes":"Lorem ipsum dolor sit amet, consectetur adipiscing elit. Nulla ac nisi nec odio"},{"words":345,"date":"2021-01-29","hours":1,"minutes":0,"mood":3,"notes":"Lorem ipsum dolor sit amet, consectetur adipiscing elit. Nulla ac nisi nec odio"},{"words":607,"date":"2021-01-30","hours":20,"minutes":18,"mood":0,"notes":"Lorem ipsum dolor sit amet, consectetur adipiscing elit. Nulla ac nisi nec odio"},{"words":90,"date":"2021-01-31","hours":16,"minutes":44,"mood":0,"notes":"Lorem ipsum dolor sit amet, consectetur adipiscing elit. Nulla ac nisi nec odio"},{"words":290,"date":"2021-01-32","hours":10,"minutes":4,"mood":4,"notes":"Lorem ipsum dolor sit amet, consectetur adipiscing elit. Nulla ac nisi nec odio"},{"words":477,"date":"2021-01-33","hours":7,"minutes":39,"mood":1,"notes":"Lorem ipsum dolor sit amet, consectetur adipiscing elit. Nulla ac nisi nec odio"},{"words":367,"date":"2021-01-34","hours":1,"minutes":29,"mood":0,"notes":"Lorem ipsum dolor sit amet, consectetur adipiscing elit. Nulla ac nisi nec odio"},{"words":300,"date":"2021-01-35","hours":3,"minutes":25,"mood":1,"notes":"Lorem ipsum dolor sit amet, consectetur adipiscing elit. Nulla ac nisi nec odio"},{"words":967,"date":"2021-01-36","hours":18,"minutes":53,"mood":4,"notes":"Lorem ipsum dolor sit amet, consectetur adipiscing elit. Nulla ac nisi nec odio"},{"words":663,"date":"2021-01-37","hours":19,"minutes":46,"mood":1,"notes":"Lorem ipsum dolor sit amet, consectetur adipiscing elit. Nulla ac nisi nec odio"},{"words":990,"date":"2021-01-38","hours":14,"minutes":29,"mood":1,"notes":"Lorem ipsum dolor sit amet, consectetur adipiscing elit. Nulla ac nisi nec odio"},{"words":402,"date":"2021-01-39","hours":5,"minutes":7,"mood":3,"notes":"Lorem ipsum dolor sit amet, consectetur adipiscing elit. Nulla ac nisi nec odio"},{"words":981,"date":"2021-01-40","hours":18,"minutes":16,"mood":4,"notes":"Lorem ipsum dolor sit amet, consectetur adipiscing elit. Nulla ac nisi nec odio"},{"words":92,"date":"2021-01-41","hours":9,"minutes":40,"mood":4,"notes":"Lorem ipsum dolor sit amet, consectetur adipiscing elit. Nulla ac nisi nec odio"},{"words":146,"date":"2021-01-42","hours":3,"minutes":54,"mood":4,"notes":"Lorem ipsum dolor sit amet, consectetur adipiscing elit. Nulla ac nisi nec odio"},{"words":394,"date":"2021-01-43","hours":4,"minutes":22,"mood":3,"notes":"Lorem ipsum dolor sit amet, consectetur adipiscing elit. Nulla ac nisi nec odio"},{"words":381,"date":"2021-01-44","hours":14,"minutes":39,"mood":4,"notes":"Lorem ipsum dolor sit amet, consectetur adipiscing elit. Nulla ac nisi nec odio"},{"words":820,"date":"2021-01-45","hours":1,"minutes":32,"mood":4,"notes":"Lorem ipsum dolor sit amet, consectetur adipiscing elit. Nulla ac nisi nec odio"},{"words":691,"date":"2021-01-46","hours":1,"minutes":49,"mood":4,"notes":"Lorem ipsum dolor sit amet, consectetur adipiscing elit. Nulla ac nisi nec odio"},{"words":829,"date":"2021-01-47","hours":4,"minutes":16,"mood":4,"notes":"Lorem ipsum dolor sit amet, consectetur adipiscing elit. Nulla ac nisi nec odio"},{"words":955,"date":"2021-01-48","hours":21,"minutes":30,"mood":0,"notes":"Lorem ipsum dolor sit amet, consectetur adipiscing elit. Nulla ac nisi nec odio"},{"words":22,"date":"2021-01-49","hours":13,"minutes":59,"mood":3,"notes":"Lorem ipsum dolor sit amet, consectetur adipiscing elit. Nulla ac nisi nec odio"},{"words":802,"date":"2021-01-50","hours":4,"minutes":54,"mood":1,"notes":"Lorem ipsum dolor sit amet, consectetur adipiscing elit. Nulla ac nisi nec odio"},{"words":196,"date":"2021-01-51","hours":9,"minutes":56,"mood":1,"notes":"Lorem ipsum dolor sit amet, consectetur adipiscing elit. Nulla ac nisi nec odio"},{"words":414,"date":"2021-01-52","hours":8,"minutes":50,"mood":1,"notes":"Lorem ipsum dolor sit amet, consectetur adipiscing elit. Nulla ac nisi nec odio"},{"words":41,"date":"2021-01-53","hours":17,"minutes":23,"mood":3,"notes":"Lorem ipsum dolor sit amet, consectetur adipiscing elit. Nulla ac nisi nec odio"},{"words":111,"date":"2021-01-54","hours":18,"minutes":25,"mood":2,"notes":"Lorem ipsum dolor sit amet, consectetur adipiscing elit. Nulla ac nisi nec odio"},{"words":678,"date":"2021-01-55","hours":15,"minutes":44,"mood":3,"notes":"Lorem ipsum dolor sit amet, consectetur adipiscing elit. Nulla ac nisi nec odio"},{"words":362,"date":"2021-01-56","hours":16,"minutes":10,"mood":1,"notes":"Lorem ipsum dolor sit amet, consectetur adipiscing elit. Nulla ac nisi nec odio"},{"words":215,"date":"2021-01-57","hours":0,"minutes":57,"mood":1,"notes":"Lorem ipsum dolor sit amet, consectetur adipiscing elit. Nulla ac nisi nec odio"},{"words":609,"date":"2021-01-58","hours":19,"minutes":52,"mood":1,"notes":"Lorem ipsum dolor sit amet, consectetur adipiscing elit. Nulla ac nisi nec odio"},{"words":469,"date":"2021-01-59","hours":9,"minutes":23,"mood":1,"notes":"Lorem ipsum dolor sit amet, consectetur adipiscing elit. Nulla ac nisi nec odio"},{"words":187,"date":"2021-01-60","hours":4,"minutes":28,"mood":4,"notes":"Lorem ipsum dolor sit amet, consectetur adipiscing elit. Nulla ac nisi nec odio"},{"words":600,"date":"2021-01-61","hours":9,"minutes":22,"mood":2,"notes":"Lorem ipsum dolor sit amet, consectetur adipiscing elit. Nulla ac nisi nec odio"},{"words":645,"date":"2021-01-62","hours":1,"minutes":29,"mood":3,"notes":"Lorem ipsum dolor sit amet, consectetur adipiscing elit. Nulla ac nisi nec odio"},{"words":461,"date":"2021-01-63","hours":16,"minutes":13,"mood":0,"notes":"Lorem ipsum dolor sit amet, consectetur adipiscing elit. Nulla ac nisi nec odio"},{"words":470,"date":"2021-01-64","hours":23,"minutes":46,"mood":1,"notes":"Lorem ipsum dolor sit amet, consectetur adipiscing elit. Nulla ac nisi nec odio"},{"words":451,"date":"2021-01-65","hours":6,"minutes":45,"mood":4,"notes":"Lorem ipsum dolor sit amet, consectetur adipiscing elit. Nulla ac nisi nec odio"},{"words":531,"date":"2021-01-66","hours":9,"minutes":54,"mood":1,"notes":"Lorem ipsum dolor sit amet, consectetur adipiscing elit. Nulla ac nisi nec odio"},{"words":236,"date":"2021-01-67","hours":2,"minutes":37,"mood":3,"notes":"Lorem ipsum dolor sit amet, consectetur adipiscing elit. Nulla ac nisi nec odio"},{"words":444,"date":"2021-01-68","hours":11,"minutes":40,"mood":3,"notes":"Lorem ipsum dolor sit amet, consectetur adipiscing elit. Nulla ac nisi nec odio"},{"words":539,"date":"2021-01-69","hours":12,"minutes":21,"mood":0,"notes":"Lorem ipsum dolor sit amet, consectetur adipiscing elit. Nulla ac nisi nec odio"},{"words":200,"date":"2021-01-70","hours":3,"minutes":40,"mood":2,"notes":"Lorem ipsum dolor sit amet, consectetur adipiscing elit. Nulla ac nisi nec odio"},{"words":57,"date":"2021-01-71","hours":6,"minutes":16,"mood":0,"notes":"Lorem ipsum dolor sit amet, consectetur adipiscing elit. Nulla ac nisi nec odio"},{"words":340,"date":"2021-01-72","hours":15,"minutes":0,"mood":1,"notes":"Lorem ipsum dolor sit amet, consectetur adipiscing elit. Nulla ac nisi nec odio"},{"words":872,"date":"2021-01-73","hours":11,"minutes":13,"mood":1,"notes":"Lorem ipsum dolor sit amet, consectetur adipiscing elit. Nulla ac nisi nec odio"},{"words":462,"date":"2021-01-74","hours":3,"minutes":0,"mood":3,"notes":"Lorem ipsum dolor sit amet, consectetur adipiscing elit. Nulla ac nisi nec odio"},{"words":136,"date":"2021-01-75","hours":20,"minutes":21,"mood":2,"notes":"Lorem ipsum dolor sit amet, consectetur adipiscing elit. Nulla ac nisi nec odio"},{"words":914,"date":"2021-01-76","hours":0,"minutes":50,"mood":2,"notes":"Lorem ipsum dolor sit amet, consectetur adipiscing elit. Nulla ac nisi nec odio"},{"words":945,"date":"2021-01-77","hours":19,"minutes":43,"mood":4,"notes":"Lorem ipsum dolor sit amet, consectetur adipiscing elit. Nulla ac nisi nec odio"},{"words":33,"date":"2021-01-78","hours":2,"minutes":41,"mood":0,"notes":"Lorem ipsum dolor sit amet, consectetur adipiscing elit. Nulla ac nisi nec odio"},{"words":319,"date":"2021-01-79","hours":15,"minutes":44,"mood":4,"notes":"Lorem ipsum dolor sit amet, consectetur adipiscing elit. Nulla ac nisi nec odio"},{"words":564,"date":"2021-01-80","hours":13,"minutes":7,"mood":2,"notes":"Lorem ipsum dolor sit amet, consectetur adipiscing elit. Nulla ac nisi nec odio"},{"words":827,"date":"2021-01-81","hours":13,"minutes":21,"mood":0,"notes":"Lorem ipsum dolor sit amet, consectetur adipiscing elit. Nulla ac nisi nec odio"},{"words":104,"date":"2021-01-82","hours":13,"minutes":12,"mood":3,"notes":"Lorem ipsum dolor sit amet, consectetur adipiscing elit. Nulla ac nisi nec odio"},{"words":140,"date":"2021-01-83","hours":23,"minutes":16,"mood":3,"notes":"Lorem ipsum dolor sit amet, consectetur adipiscing elit. Nulla ac nisi nec odio"},{"words":603,"date":"2021-01-84","hours":10,"minutes":16,"mood":0,"notes":"Lorem ipsum dolor sit amet, consectetur adipiscing elit. Nulla ac nisi nec odio"},{"words":561,"date":"2021-01-85","hours":15,"minutes":20,"mood":1,"notes":"Lorem ipsum dolor sit amet, consectetur adipiscing elit. Nulla ac nisi nec odio"},{"words":819,"date":"2021-01-86","hours":23,"minutes":56,"mood":1,"notes":"Lorem ipsum dolor sit amet, consectetur adipiscing elit. Nulla ac nisi nec odio"},{"words":238,"date":"2021-01-87","hours":7,"minutes":5,"mood":2,"notes":"Lorem ipsum dolor sit amet, consectetur adipiscing elit. Nulla ac nisi nec odio"},{"words":69,"date":"2021-01-88","hours":4,"minutes":36,"mood":3,"notes":"Lorem ipsum dolor sit amet, consectetur adipiscing elit. Nulla ac nisi nec odio"},{"words":290,"date":"2021-01-89","hours":4,"minutes":18,"mood":4,"notes":"Lorem ipsum dolor sit amet, consectetur adipiscing elit. Nulla ac nisi nec odio"},{"words":403,"date":"2021-01-90","hours":14,"minutes":5,"mood":1,"notes":"Lorem ipsum dolor sit amet, consectetur adipiscing elit. Nulla ac nisi nec odio"},{"words":616,"date":"2021-01-91","hours":2,"minutes":39,"mood":2,"notes":"Lorem ipsum dolor sit amet, consectetur adipiscing elit. Nulla ac nisi nec odio"},{"words":737,"date":"2021-01-92","hours":2,"minutes":0,"mood":3,"notes":"Lorem ipsum dolor sit amet, consectetur adipiscing elit. Nulla ac nisi nec odio"},{"words":981,"date":"2021-01-93","hours":2,"minutes":54,"mood":2,"notes":"Lorem ipsum dolor sit amet, consectetur adipiscing elit. Nulla ac nisi nec odio"},{"words":999,"date":"2021-01-94","hours":0,"minutes":5,"mood":1,"notes":"Lorem ipsum dolor sit amet, consectetur adipiscing elit. Nulla ac nisi nec odio"},{"words":600,"date":"2021-01-95","hours":12,"minutes":32,"mood":4,"notes":"Lorem ipsum dolor sit amet, consectetur adipiscing elit. Nulla ac nisi nec odio"},{"words":885,"date":"2021-01-96","hours":11,"minutes":58,"mood":4,"notes":"Lorem ipsum dolor sit amet, consectetur adipiscing elit. Nulla ac nisi nec odio"},{"words":612,"date":"2021-01-97","hours":7,"minutes":36,"mood":4,"notes":"Lorem ipsum dolor sit amet, consectetur adipiscing elit. Nulla ac nisi nec odio"},{"words":991,"date":"2021-01-98","hours":13,"minutes":58,"mood":3,"notes":"Lorem ipsum dolor sit amet, consectetur adipiscing elit. Nulla ac nisi nec odio"},{"words":853,"date":"2021-01-99","hours":14,"minutes":55,"mood":1,"notes":"Lorem ipsum dolor sit amet, consectetur adipiscing elit. Nulla ac nisi nec odio"},{"words":20,"date":"2021-01-100","hours":9,"minutes":10,"mood":3,"notes":"Lorem ipsum dolor sit amet, consectetur adipiscing elit. Nulla ac nisi nec odio"}]},"length":10000}